tailblazer/__init__.py
tailblazer/compute.py
tailblazer-0.0.1.dist-info/LICENSE
tailblazer-0.0.1.dist-info/METADATA
tailblazer-0.0.1.dist-info/WHEEL
tailblazer-0.0.1.dist-info/top_level.txt
tailblazer-0.0.1.dist-info/RECORD
