Metadata-Version: 2.1
Name: tailblazer
Version: 0.0.1
Summary: A collection of NumPy compatible algorithms for working with the tails of distributions.
Author-email: Chris Walker <walkerjameschris@gmail.com>
Project-URL: Homepage, https://github.com/pypa/sampleproject
Project-URL: Issues, https://github.com/pypa/sampleproject/issues
Classifier: Programming Language :: Python :: 3
Classifier: License :: OSI Approved :: MIT License
Classifier: Operating System :: OS Independent
Requires-Python: >=3.8
License-File: LICENSE
Requires-Dist: numpy
